{
	"format_version": "1.8.0",
	"animations": {
		"garden.idle": {
			"loop": true,
			"animation_length": 4,
			"bones": {
				"scareflower": {
					"rotation": {
						"0.0": {
							"vector": [0, 0, 0]
						},
						"1.0": {
							"vector": [0, 0, -5],
							"easing": "easeOutBack"
						},
						"3.0": {
							"vector": [0, 0, 7.5],
							"easing": "easeInBack"
						},
						"4.0": {
							"vector": [0, 0, 0],
							"easing": "easeInBack"
						}
					},
					"position": {
						"0.0": {
							"vector": [0, 0, 0]
						},
						"1.0": {
							"vector": [0, -0.5, 0],
							"easing": "easeOutBack"
						},
						"3.0": {
							"vector": [0, -0.5, 0],
							"easing": "easeInBack"
						},
						"4.0": {
							"vector": [0, 0, 0],
							"easing": "easeInBack"
						}
					},
					"scale": {
						"0.0": {
							"vector": [1, 1, 1]
						},
						"1.0": {
							"vector": [1, 1.1, 1],
							"easing": "easeOutBack"
						},
						"2.0": {
							"vector": [1, 1, 1],
							"easing": "linear"
						},
						"3.0": {
							"vector": [1, 1.1, 1],
							"easing": "easeInBack"
						},
						"4.0": {
							"vector": [1, 1, 1],
							"easing": "easeInBack"
						}
					}
				},
				"armleft": {
					"rotation": {
						"0.0": {
							"vector": [0, 0, 0]
						},
						"1.0": {
							"vector": [0, 0, -50],
							"easing": "easeOutBack"
						},
						"2.0": {
							"vector": [0, 0, 0],
							"easing": "linear"
						},
						"3.0": {
							"vector": [0, 0, -50],
							"easing": "easeInBack"
						},
						"4.0": {
							"vector": [0, 0, 0],
							"easing": "easeInBack"
						}
					},
					"position": {
						"0.0": {
							"vector": [0, 0, 0]
						},
						"1.0": {
							"vector": [-1.6, -1.1, 0],
							"easing": "easeOutBack"
						},
						"2.0": {
							"vector": [0, 0, 0],
							"easing": "linear"
						},
						"3.0": {
							"vector": [-1.6, -1.1, 0],
							"easing": "easeInBack"
						},
						"4.0": {
							"vector": [0, 0, 0],
							"easing": "easeInBack"
						}
					},
					"scale": {
						"0.0": {
							"vector": [1, 1, 1]
						},
						"4.0": {
							"vector": [1, 1, 1],
							"easing": "easeInBack"
						}
					}
				},
				"armright": {
					"rotation": {
						"0.0": {
							"vector": [0, 0, 0]
						},
						"1.0": {
							"vector": [0, 0, 17.5],
							"easing": "easeOutBack"
						},
						"2.0": {
							"vector": [0, 0, 0],
							"easing": "linear"
						},
						"3.0": {
							"vector": [0, 0, 17.5],
							"easing": "easeInBack"
						},
						"4.0": {
							"vector": [0, 0, 0],
							"easing": "easeInBack"
						}
					},
					"position": {
						"0.0": {
							"vector": [0, 0, 0]
						},
						"1.0": {
							"vector": [0.9, 0, 0],
							"easing": "easeOutBack"
						},
						"2.0": {
							"vector": [0, 0, 0],
							"easing": "linear"
						},
						"3.0": {
							"vector": [0.9, 0, 0],
							"easing": "easeInBack"
						},
						"4.0": {
							"vector": [0, 0, 0],
							"easing": "easeInBack"
						}
					},
					"scale": {
						"0.0": {
							"vector": [1, 1, 1]
						},
						"4.0": {
							"vector": [1, 1, 1],
							"easing": "easeInBack"
						}
					}
				}
			}
		}
	},
	"geckolib_format_version": 2
}